topsis/__init__.py
topsis/__main__.py
102218041_topsis-1.0.0.dist-info/LICENSE
102218041_topsis-1.0.0.dist-info/METADATA
102218041_topsis-1.0.0.dist-info/WHEEL
102218041_topsis-1.0.0.dist-info/entry_points.txt
102218041_topsis-1.0.0.dist-info/top_level.txt
102218041_topsis-1.0.0.dist-info/RECORD
