Metadata-Version: 2.1
Name: 102218041-topsis
Version: 1.0.0
Summary: A Python implementation of the TOPSIS method for multi-criteria decision making
Home-page: https://github.com/Eshitva/102218041_Eshitva_TOPSIS
Author: Eshitva
Author-email: goyaleshitva@gmail.com
Classifier: Programming Language :: Python :: 3
Classifier: License :: OSI Approved :: MIT License
Classifier: Operating System :: OS Independent
Requires-Python: >=3.6
License-File: LICENSE
Requires-Dist: numpy
